flextaxd/__init__.py
flextaxd/create_databases.py
flextaxd/custom_taxonomy_databases.py
flextaxd/modules/CreateCentrifugeDB.py
flextaxd/modules/CreateGanonDB.py
flextaxd/modules/CreateKrakenDatabase.py
flextaxd/modules/ModifyTree.py
flextaxd/modules/PhylogenyDB.py
flextaxd/modules/ReadTaxonomy.py
flextaxd/modules/ReadTaxonomyCanSNPer.py
flextaxd/modules/ReadTaxonomyNCBI.py
flextaxd/modules/ReadTaxonomyQIIME.py
flextaxd/modules/WriteNewick.py
flextaxd/modules/WriteTaxonomy.py
flextaxd/modules/__init__.py
flextaxd/modules/database/CreateDatabase.py
flextaxd/modules/database/DatabaseConnection.py
flextaxd/modules/database/__init__.py
flextaxd-0.1.5.dist-info/LICENSE
flextaxd-0.1.5.dist-info/METADATA
flextaxd-0.1.5.dist-info/WHEEL
flextaxd-0.1.5.dist-info/entry_points.txt
flextaxd-0.1.5.dist-info/top_level.txt
flextaxd-0.1.5.dist-info/RECORD
