Metadata-Version: 2.1
Name: flextaxd
Version: 0.1.5
Summary: Script that allows the creation of custom kraken databases from various sources (NCBI, QIIME, CanSNPer)
Home-page: https://github.com/FOI-Bioinformatics/flextaxd
Author: David Sundell
Author-email: david.sundell@foi.se
License: GNU GENERAL PUBLIC LICENSE version 3
Keywords: taxonomy NCBI CanSNPer customization GTDB
Platform: UNKNOWN
Classifier: Programming Language :: Python :: 3
Classifier: License :: OSI Approved :: GNU General Public License v3 (GPLv3)
Classifier: Operating System :: OS Independent
Requires-Python: >=3.6
